payment_page_sdk/__init__.py
payment_page_sdk/callback.py
payment_page_sdk/cipher.py
payment_page_sdk/gate.py
payment_page_sdk/payment.py
payment_page_sdk/payment_page.py
payment_page_sdk/process_exception.py
payment_page_sdk/signature_handler.py
gtxpoint_sdk-1.0.1.dist-info/LICENSE
gtxpoint_sdk-1.0.1.dist-info/METADATA
gtxpoint_sdk-1.0.1.dist-info/WHEEL
gtxpoint_sdk-1.0.1.dist-info/top_level.txt
gtxpoint_sdk-1.0.1.dist-info/RECORD
